[
  {
    "line": 1,
    "elements": [
      {
        "start_timestamp": "2021-07-04T10:36:26.747Z",
        "line": 14,
        "name": "Verify if Place is being succcessfully added using ADD API\u0027s",
        "description": "",
        "id": "validating-place-api-s;verify-if-place-is-being-succcessfully-added-using-add-api-s;;2",
        "type": "scenario",
        "keyword": "Scenario Outline",
        "steps": [
          {
            "result": {
              "duration": 1886000000,
              "status": "passed"
            },
            "line": 5,
            "name": "Add Place Payload with \"Frontline house\" \"29, side layout, cohen 09\" \"French-IN\"",
            "match": {
              "arguments": [
                {
                  "val": "\"Frontline house\"",
                  "offset": 23
                },
                {
                  "val": "\"29, side layout, cohen 09\"",
                  "offset": 41
                },
                {
                  "val": "\"French-IN\"",
                  "offset": 69
                }
              ],
              "location": "stepDefinations.StepDefination.add_place_payload_with_something_something_something(java.lang.String,java.lang.String,java.lang.String)"
            },
            "keyword": "Given "
          },
          {
            "result": {
              "duration": 2715000000,
              "status": "passed"
            },
            "line": 6,
            "name": "User Calls \"addPlaceAPI\" API with \"post\" http request",
            "match": {
              "arguments": [
                {
                  "val": "\"addPlaceAPI\"",
                  "offset": 11
                },
                {
                  "val": "\"post\"",
                  "offset": 34
                }
              ],
              "location": "stepDefinations.StepDefination.user_calls_api_with_method_http_request(java.lang.String,java.lang.String)"
            },
            "keyword": "When "
          },
          {
            "result": {
              "duration": 2000000,
              "status": "passed"
            },
            "line": 7,
            "name": "The API call got success with status code 200",
            "match": {
              "arguments": [
                {
                  "val": "200",
                  "offset": 42
                }
              ],
              "location": "stepDefinations.StepDefination.the_api_call_got_success_with_status_code(int)"
            },
            "keyword": "Then "
          },
          {
            "result": {
              "duration": 1270000000,
              "status": "passed"
            },
            "line": 8,
            "name": "\"status\" in response body is \"OK\"",
            "match": {
              "arguments": [
                {
                  "val": "\"status\"",
                  "offset": 0
                },
                {
                  "val": "\"OK\"",
                  "offset": 29
                }
              ],
              "location": "stepDefinations.StepDefination.in_response_body_is(java.lang.String,java.lang.String)"
            },
            "keyword": "And "
          },
          {
            "result": {
              "duration": 36000000,
              "status": "passed"
            },
            "line": 9,
            "name": "\"scope\" in response body is \"APP\"",
            "match": {
              "arguments": [
                {
                  "val": "\"scope\"",
                  "offset": 0
                },
                {
                  "val": "\"APP\"",
                  "offset": 28
                }
              ],
              "location": "stepDefinations.StepDefination.in_response_body_is(java.lang.String,java.lang.String)"
            },
            "keyword": "And "
          },
          {
            "result": {
              "duration": 2095000000,
              "status": "passed"
            },
            "line": 10,
            "name": "verify \"place_id\" created maps to \"Frontline house\" using \"getPlaceAPI\"",
            "match": {
              "arguments": [
                {
                  "val": "\"place_id\"",
                  "offset": 7
                },
                {
                  "val": "\"Frontline house\"",
                  "offset": 34
                },
                {
                  "val": "\"getPlaceAPI\"",
                  "offset": 58
                }
              ],
              "location": "stepDefinations.StepDefination.verify_place_id_created_maps_to_using(java.lang.String,java.lang.String,java.lang.String)"
            },
            "keyword": "And "
          }
        ],
        "tags": [
          {
            "name": "@AddPlace"
          },
          {
            "name": "@Regression"
          }
        ]
      }
    ],
    "name": "Validating Place API\u0027s",
    "description": "",
    "id": "validating-place-api-s",
    "keyword": "Feature",
    "uri": "file:src/test/java/features/placeValidations.feature",
    "tags": []
  }
]